rtl/decrypt.v
// ============================================================
// Decryption
// P = C ⊕ Z
// ============================================================

module DECRYPT (
    input  wire ciphertext,
    input  wire Z,
    output wire plaintext_out
);

    assign plaintext_out = ciphertext ^ Z;

endmodule

flow_45nm_open_source/rtl/encrypt.v
// ============================================================
// Encryption
// C = P ⊕ Z
// ============================================================

module ENCRYPT (
    input  wire plaintext,
    input  wire Z,
    output wire ciphertext
);

    assign ciphertext = plaintext ^ Z;

endmodule

flow_45nm_open_source/rtl/keystream.v
// ============================================================
// Output Logic Z
// Z = L2 ⊕ N3 ⊕ (L7·N4) ⊕ (L1·N6)
// ============================================================

module KEYSTREAM (
    input  wire [7:0] L,
    input  wire [7:0] N,
    output wire Z
);

    assign Z = L[2] ^
               N[3] ^
               (L[7] & N[4]) ^
               (L[1] & N[6]);

endmodule

NFSR.v
// ============================================================
// 8-bit NFSR
// fN = N7 ⊕ (N5·N3) ⊕ ((N2·N1) ⊕ L4)
// ============================================================

module NFSR (
    input  wire clk,
    input  wire rst,
    input  wire L4,
    output reg  [7:0] N
);

    wire nonlinear1;
    wire nonlinear2;
    wire feedback;

    assign nonlinear1 = N[5] & N[3];
    assign nonlinear2 = (N[2] & N[1]) ^ L4;

    assign feedback = N[7] ^ nonlinear1 ^ nonlinear2;

    always @(posedge clk) begin
        if (rst)
            N <= 8'b11011010;
        else
            N <= {N[6:0], feedback};
    end

endmodule

LFSR.v
// ============================================================
// 8-bit LFSR
// fL = L7 ⊕ L5 ⊕ L4 ⊕ L3
// ============================================================

module LFSR (
    input  wire clk,
    input  wire rst,
    output reg  [7:0] L
);

    wire feedback;

    assign feedback = L[7] ^ L[5] ^ L[4] ^ L[3];

    always @(posedge clk) begin
        if (rst)
            L <= 8'b10101101;
        else
            L <= {L[6:0], feedback};
    end

endmodule

rtl/lfsr_nfsr_top.v
// ============================================================
// Top Integration Module
// ============================================================

module lfsr_nfsr_top (
    input  wire clk,
    input  wire rst,
    input  wire plaintext,
    output wire ciphertext,
    output wire decrypted_text
);

    wire [7:0] L;
    wire [7:0] N;
    wire Z;

    // LFSR
    LFSR lfsr_inst (
        .clk(clk),
        .rst(rst),
        .L(L)
    );

    // NFSR
    NFSR nfsr_inst (
        .clk(clk),
        .rst(rst),
        .L4(L[4]),
        .N(N)
    );

    // Keystream
    KEYSTREAM ks_inst (
        .L(L),
        .N(N),
        .Z(Z)
    );

    // Encryption
    ENCRYPT enc_inst (
        .plaintext(plaintext),
        .Z(Z),
        .ciphertext(ciphertext)
    );

    // Decryption
    DECRYPT dec_inst (
        .ciphertext(ciphertext),
        .Z(Z),
        .plaintext_out(decrypted_text)
    );

endmodule

tb/tb_lfsr_nfsr.v
`timescale 1ns/1ps

module TB;

reg clk;
reg rst;
reg plaintext;

wire ciphertext;
wire decrypted_text;

// Instantiate Top Module
lfsr_nfsr_top dut (
    .clk(clk),
    .rst(rst),
    .plaintext(plaintext),
    .ciphertext(ciphertext),
    .decrypted_text(decrypted_text)
);

// Clock Generation
always #5 clk = ~clk;

initial begin
    $dumpfile("wave.vcd");
    $dumpvars(0, TB);

    clk = 0;
    rst = 1;
    plaintext = 0;

    #10 rst = 0;

    #10 plaintext = 1;
    #20 plaintext = 0;
    #20 plaintext = 1;
    #20 plaintext = 1;
    #20 plaintext = 0;

    #50 $finish;
end

endmodule

wave.vcd
$date
	Sun Mar  1 21:11:19 2026
$end
$version
	Icarus Verilog
$end
$timescale
	1ps
$end
$scope module TB $end
$var wire 1 ! decrypted_text $end
$var wire 1 " ciphertext $end
$var reg 1 # clk $end
$var reg 1 $ plaintext $end
$var reg 1 % rst $end
$scope module dut $end
$var wire 1 # clk $end
$var wire 1 $ plaintext $end
$var wire 1 % rst $end
$var wire 1 ! decrypted_text $end
$var wire 1 " ciphertext $end
$var wire 1 & Z $end
$var wire 8 ' N [7:0] $end
$var wire 8 ( L [7:0] $end
$scope module dec_inst $end
$var wire 1 ! plaintext_out $end
$var wire 1 " ciphertext $end
$var wire 1 & Z $end
$upscope $end
$scope module enc_inst $end
$var wire 1 " ciphertext $end
$var wire 1 $ plaintext $end
$var wire 1 & Z $end
$upscope $end
$scope module ks_inst $end
$var wire 1 & Z $end
$var wire 8 ) N [7:0] $end
$var wire 8 * L [7:0] $end
$upscope $end
$scope module lfsr_inst $end
$var wire 1 # clk $end
$var wire 1 + feedback $end
$var wire 1 % rst $end
$var reg 8 , L [7:0] $end
$upscope $end
$scope module nfsr_inst $end
$var wire 1 - L4 $end
$var wire 1 # clk $end
$var wire 1 . feedback $end
$var wire 1 / nonlinear1 $end
$var wire 1 0 nonlinear2 $end
$var wire 1 % rst $end
$var reg 8 1 N [7:0] $end
$upscope $end
$upscope $end
$upscope $end
$enddefinitions $end
$comment Show the parameter values. $end
$dumpall
$end
#0
$dumpvars
bx 1
x0
x/
x.
x-
bx ,
x+
bx *
bx )
bx (
bx '
x&
1%
0$
0#
x"
x!
$end
#5000
0!
1+
1"
1.
1&
00
0/
0-
b10101101 (
b10101101 *
b10101101 ,
b11011010 '
b11011010 )
b11011010 1
1#
#10000
0#
0%
#15000
0"
0!
0&
0+
0.
10
1-
b10110101 '
b10110101 )
b10110101 1
b1011011 (
b1011011 *
b1011011 ,
1#
#20000
1!
1"
0#
1$
#25000
0"
1!
0.
1&
1+
1/
b10110110 (
b10110110 *
b10110110 ,
b1101010 '
b1101010 )
b1101010 1
1#
#30000
0#
#35000
1.
0"
1!
1&
0/
0+
00
0-
b11010100 '
b11010100 )
b11010100 1
b1101101 (
b1101101 *
b1101101 ,
1#
#40000
0!
1"
0#
0$
#45000
1+
10
1/
1-
b11011010 (
b11011010 *
b11011010 ,
b10101001 '
b10101001 )
b10101001 1
1#
#50000
0#
#55000
0"
0!
0&
1.
0/
1+
b1010011 '
b1010011 )
b1010011 1
b10110101 (
b10110101 *
b10110101 ,
1#
#60000
1!
1"
0#
1$
#65000
0.
0+
0-
b1101011 (
b1101011 *
b1101011 ,
b10100111 '
b10100111 )
b10100111 1
1#
#70000
0#
#75000
0"
1!
1&
0+
00
1-
b1001110 '
b1001110 )
b1001110 1
b11010110 (
b11010110 *
b11010110 ,
1#
#80000
0#
#85000
1.
1+
0-
b10101100 (
b10101100 *
b10101100 ,
b10011100 '
b10011100 )
b10011100 1
1#
#90000
0#
#95000
0.
0+
1/
10
1-
b111001 '
b111001 )
b111001 1
b1011001 (
b1011001 *
b1011001 ,
1#
#100000
0!
1"
0#
0$
#105000
1.
0"
0!
0&
1+
0/
b10110010 (
b10110010 *
b10110010 ,
b1110010 '
b1110010 )
b1110010 1
1#
#110000
0#
#115000
1"
0!
1+
1&
00
0-
b11100101 '
b11100101 )
b11100101 1
b1100101 (
b1100101 *
b1100101 ,
1#
#120000
0#
#125000
0"
0!
0&
0+
b11001011 (
b11001011 *
b11001011 ,
b11001011 '
b11001011 )
b11001011 1
1#
#130000
0#
#135000
1.
0+
00
1-
b10010111 '
b10010111 )
b10010111 1
b10010110 (
b10010110 *
b10010110 ,
1#
#140000
0#
#145000
0.
0+
10
1/
0-
b101100 (
b101100 *
b101100 ,
b101111 '
b101111 )
b101111 1
1#
